lairgpt/__init__.py
lairgpt/gpt_model.py
lairgpt/models.py
lairgpt/text_generator.py
lairgpt/blocks/__init__.py
lairgpt/blocks/blocks.py
lairgpt/utils/__init__.py
lairgpt/utils/assets.py
lairgpt/utils/mask.py
lairgpt/utils/remote.py
lairgpt-0.5.2.dist-info/LICENSE
lairgpt-0.5.2.dist-info/METADATA
lairgpt-0.5.2.dist-info/WHEEL
lairgpt-0.5.2.dist-info/top_level.txt
lairgpt-0.5.2.dist-info/RECORD
