Metadata-Version: 2.1
Name: lairgpt
Version: 0.5.2
Summary: A Pytorch-based package by LightOn AI Research allowing to perform inference with PAGnol models.
Home-page: https://github.com/lightonai/lairgpt
Author: Lighton AI Research
Author-email: iacopo@lighton.io,julien@lighton.io,igor@lighton.io
License: UNKNOWN
Platform: UNKNOWN
Classifier: Programming Language :: Python
Classifier: Programming Language :: Python :: 3
Classifier: Programming Language :: Python :: 3.9
Classifier: Programming Language :: Python :: 3.10
Classifier: Topic :: Scientific/Engineering :: Artificial Intelligence
Classifier: Intended Audience :: Science/Research
Classifier: License :: OSI Approved :: MIT License
Requires-Dist: torch (==1.8.*)
Requires-Dist: tokenizers (==0.10)
Requires-Dist: wget (==3.2)
